capitalbudgeting/__init__.py
capitalbudgeting-0.1.0.dist-info/licenses/LICENSE
capitalbudgeting-0.1.0.dist-info/METADATA
capitalbudgeting-0.1.0.dist-info/WHEEL
capitalbudgeting-0.1.0.dist-info/top_level.txt
capitalbudgeting-0.1.0.dist-info/RECORD
