Metadata-Version: 2.4
Name: capitalbudgeting
Version: 0.1.0
Summary: Indicators for capital budgeting: npv, irr, mirr, ipp, etc
Author-email: Rho Zhang <rhozhang@163.com>
License-Expression: MIT
Project-URL: Homepage, https://github.com/rhozhang/capitalbudgeting
Project-URL: Issues, https://github.com/rhozhang/capitalbudgeting/issues
Classifier: Programming Language :: Python :: 3
Classifier: Operating System :: OS Independent
Requires-Python: >=3.12
License-File: LICENSE
Dynamic: license-file
